{
  "hash": "4a078f4a42ce7f04a0bf65c85c5a51d7",
  "result": {
    "engine": "knitr",
    "markdown": "---\ntitle: \"Basic Biostatistics & Bioinformatics\"\ndescription: |\n  practical concepts and coding for everyone\n---\n\n\n::: {layout-ncol=2}\n<br>\nSLUBI and the SLU Centre for Statistics are bringing you a new series focused on R and applications in bioinformatics.\\\n  <b>Mondays in even weeks, 09:45 </b>\\\n  <b>Campus Alnarp, Horticum </b>\\\n  <b>or via [Zoom](https://slu-se.zoom.us/j/69486568642) (Password: 410 410) </b>\n\n![](images/3bees_opaque.png){.class width=80%}\n:::\n\nWe are starting a topic-driven discussion series where Adam Flöhr from the Centre for Statistics will discuss the statistical magic behind some of the common methods we use, and Lizel Potgieter from SLUBI will use data to show a hands-on example of how to execute the analyses. \\\n\nAll data and codes will be available at https://github.com/SLUBioinformaticsInfrastructure/Three_Bees_Workshop_Series.\n\n<br>\n**Program** \\\n\n\n\n::: {.cell}\n::: {.cell-output-display}\n`````{=html}\n<table class=\" lightable-material lightable-striped lightable-hover\" style='font-family: \"Source Sans Pro\", helvetica, sans-serif; margin-left: auto; margin-right: auto;'>\n <thead>\n  <tr>\n   <th style=\"text-align:left;\"> Date </th>\n   <th style=\"text-align:left;\"> Topic </th>\n  </tr>\n </thead>\n<tbody>\n  <tr>\n   <td style=\"text-align:left;\"> 13th Nov 2023 </td>\n   <td style=\"text-align:left;\"> Introduction to R </td>\n  </tr>\n  <tr>\n   <td style=\"text-align:left;\"> 27th Nov 2023 </td>\n   <td style=\"text-align:left;\"> Linux Basics </td>\n  </tr>\n  <tr>\n   <td style=\"text-align:left;\"> 11th Dec 2023 </td>\n   <td style=\"text-align:left;\"> Theory and practice PCA </td>\n  </tr>\n  <tr>\n   <td style=\"text-align:left;\"> 15th Jan 2024 </td>\n   <td style=\"text-align:left;\"> Introduction to Markdown </td>\n  </tr>\n  <tr>\n   <td style=\"text-align:left;\"> 12th Feb 2024 </td>\n   <td style=\"text-align:left;\"> Population Structure </td>\n  </tr>\n  <tr>\n   <td style=\"text-align:left;\"> 26th Feb 2024 </td>\n   <td style=\"text-align:left;\"> Functions in R </td>\n  </tr>\n  <tr>\n   <td style=\"text-align:left;\"> 11th March 2024 </td>\n   <td style=\"text-align:left;\"> Introduction to Python </td>\n  </tr>\n  <tr>\n   <td style=\"text-align:left;\"> 25th Match 2024 </td>\n   <td style=\"text-align:left;\"> Introduction to Machine Learning </td>\n  </tr>\n  <tr>\n   <td style=\"text-align:left;\"> 8th April 2024 </td>\n   <td style=\"text-align:left;\"> Intermediate ggplot in R </td>\n  </tr>\n</tbody>\n</table>\n\n`````\n:::\n:::\n\n\n<br>\nWe want to serve the SLU bioinformatics communities, so the floor to topic suggestions is open: \n\nPlease fill out [this questionnaire](https://forms.gle/4juDXf3tK8dSxmpe8) to decide what you would like to hear (more) about. \n\n",
    "supporting": [],
    "filters": [
      "rmarkdown/pagebreak.lua"
    ],
    "includes": {
      "include-in-header": [
        "<script src=\"site_libs/kePrint-0.0.1/kePrint.js\"></script>\n<link href=\"site_libs/lightable-0.0.1/lightable.css\" rel=\"stylesheet\" />\n"
      ]
    },
    "engineDependencies": {},
    "preserve": {},
    "postProcess": true
  }
}